{
  "active_plan": "/home/berke/opencode-limit-reset/.sisyphus/plans/oplire-reset.md",
  "started_at": "2026-04-11T11:30:00.000Z",
  "session_ids": [
    "ses_283bbe6a5ffewvaBD0GjOgM6x4"
  ],
  "plan_name": "oplire-reset",
  "worktree_path": null,
  "session_origins": {
    "ses_283bbe6a5ffewvaBD0GjOgM6x4": "direct"
  },
  "task_sessions": {
    "todo:1": {
      "task_key": "todo:1",
      "task_label": "1",
      "task_title": "Project Scaffolding",
      "session_id": "ses_283b0f17bffenbyv20AUYd4RAY",
      "agent": "Sisyphus-Junior",
      "category": "quick",
      "updated_at": "2026-04-11T11:32:14.386Z"
    },
    "todo:2": {
      "task_key": "todo:2",
      "task_label": "2",
      "task_title": "CLI Structure with Clap",
      "session_id": "ses_283af39cfffeVHrzumQCp1aN1G",
      "agent": "Sisyphus-Junior",
      "category": "quick",
      "updated_at": "2026-04-11T11:33:05.853Z"
    },
    "todo:3": {
      "task_key": "todo:3",
      "task_label": "3",
      "task_title": "Modern README Documentation",
      "session_id": "ses_283ae50ebffe5AgN3s9aqGVrSq",
      "agent": "Sisyphus-Junior",
      "category": "writing",
      "updated_at": "2026-04-11T11:34:25.470Z"
    },
    "todo:5": {
      "task_key": "todo:5",
      "task_label": "5",
      "task_title": "WARP Reset Logic (Core)",
      "session_id": "ses_283a889adffeR6CNHN8G3n3mo5",
      "agent": "Sisyphus-Junior",
      "category": "quick",
      "updated_at": "2026-04-11T11:41:10.269Z"
    },
    "final-wave:f1": {
      "task_key": "final-wave:f1",
      "task_label": "F1",
      "task_title": "**Plan Compliance Audit** — `oracle`",
      "session_id": "ses_283a5d347ffe1ARtL2mKzvgYDW",
      "agent": "Sisyphus-Junior",
      "category": "quick",
      "updated_at": "2026-04-11T11:43:10.884Z"
    }
  }
}